Metadata-Version: 2.1
Name: entity-everything
Version: 2.0.1
Summary: Python tool for encoding text to HTML entities
Home-page: UNKNOWN
Author: Daniel Rogowski
License: UNKNOWN
Platform: UNKNOWN
Classifier: Programming Language :: Python :: 3
Classifier: License :: OSI Approved :: MIT License
Classifier: Operating System :: OS Independent
Requires-Python: >=3.9
License-File: LICENSE.txt
